pandora/__init__.py
pandora/_pkgdetails.py
pandora/core/__init__.py
pandora/core/accuracy/__init__.py
pandora/core/accuracy/binary_classification.py
pandora/core/preprocessor/__init__.py
pandora/core/preprocessor/text.py
pandora/models/__init__.py
pandora/pipeline/__init__.py
pandora/pipeline/handler.py
pandora/pipeline/pipeline.py
pandora/pipeline/validator.py
pandora/util/__init__.py
pandora/util/dataframe.py
pandora/util/datatype.py
pandora/util/io.py
pandora/util/memory.py
pandora/util/transformation.py
pandora/util/validate.py
pandora_python-0.0.1.dist-info/METADATA
pandora_python-0.0.1.dist-info/WHEEL
pandora_python-0.0.1.dist-info/top_level.txt
pandora_python-0.0.1.dist-info/RECORD
